xcwarnings/__init__.py
xcwarnings/build_warning.py
xcwarnings/build_warning_diff.py
xcwarnings/build_warning_diff_report.py
xcwarnings/build_warning_scope.py
xcwarnings/logger.py
xcwarnings-0.3.0.dist-info/LICENSE
xcwarnings-0.3.0.dist-info/METADATA
xcwarnings-0.3.0.dist-info/WHEEL
xcwarnings-0.3.0.dist-info/RECORD
