Metadata-Version: 2.1
Name: xcwarnings
Version: 0.3.0
Summary: Xcode Warnings Quality Gate
License: MIT
Author: Rayyan Jabbar
Author-email: rajaber@microsoft.com
Requires-Python: >=3.10,<4.0
Classifier: License :: OSI Approved :: MIT License
Classifier: Programming Language :: Python :: 3
Classifier: Programming Language :: Python :: 3.10
Classifier: Programming Language :: Python :: 3.11
Classifier: Programming Language :: Python :: 3.12
